goodbye/__init__.py
goodbye/core.py
goodbye_bro-0.1.2.dist-info/METADATA
goodbye_bro-0.1.2.dist-info/WHEEL
goodbye_bro-0.1.2.dist-info/top_level.txt
goodbye_bro-0.1.2.dist-info/RECORD
