Metadata-Version: 2.4
Name: goodbye-bro
Version: 0.1.2
Summary: A tiny Python library that says Goodbye, World!
Author: bro
License: MIT
Project-URL: Homepage, https://pypi.org/project/goodbye-bro/
Classifier: Programming Language :: Python :: 3
Classifier: License :: OSI Approved :: MIT License
Classifier: Operating System :: OS Independent
Requires-Python: >=3.8
